{
  "address": "",
  "description": "Da Pizza Dude is here to serve you pizza with attitude! A delicious meal and an entertainment experience, marvel as Da Dude creates his delicious cuisine! Whether you're looking for classic Italian-style pizza or something with a real modern twist, Da Pizza Dude is here for you!",
  "exampleOrder": "",
  "hours": [
    {
      "closeTime": "",
      "day": "Monday",
      "openTime": ""
    },
    {
      "closeTime": "",
      "day": "Tuesday",
      "openTime": ""
    },
    {
      "closeTime": "",
      "day": "Wednesday",
      "openTime": ""
    },
    {
      "closeTime": "",
      "day": "Thursday",
      "openTime": ""
    },
    {
      "closeTime": "",
      "day": "Friday",
      "openTime": ""
    },
    {
      "closeTime": "",
      "day": "Saturday",
      "openTime": ""
    },
    {
      "closeTime": "",
      "day": "Sunday",
      "openTime": ""
    }
  ],
  "name": "Da Pizza Dude",
  "optional": {
    "producer": {
      "enabled": true,
      "menuLink": "",
      "phoneNumber": ""
    }
  },
  "password": "",
  "percentageFee": 6,
  "profileImage": "http://roaminghunger.com/img/trucks/original/55899283-f0e4-465d-b537-65a746204482.jpg",
  "transactionFee": 30,
  "username": ""
}