{
  "address": "",
  "description": "This vibrant truck is roaming through Denver and dishing the delicious flavors of Venezuela. With amazingly authentic Arepas, Empanadas, and Plantains, it\u2019s no wonder why local foodies just can\u2019t contain their adoration for Arepas House. ",
  "exampleOrder": "",
  "hours": [
    {
      "closeTime": "",
      "day": "Monday",
      "openTime": ""
    },
    {
      "closeTime": "",
      "day": "Tuesday",
      "openTime": ""
    },
    {
      "closeTime": "",
      "day": "Wednesday",
      "openTime": ""
    },
    {
      "closeTime": "",
      "day": "Thursday",
      "openTime": ""
    },
    {
      "closeTime": "",
      "day": "Friday",
      "openTime": ""
    },
    {
      "closeTime": "",
      "day": "Saturday",
      "openTime": ""
    },
    {
      "closeTime": "",
      "day": "Sunday",
      "openTime": ""
    }
  ],
  "name": "AREPAS HOUSE",
  "optional": {
    "producer": {
      "enabled": true,
      "menuLink": "",
      "phoneNumber": ""
    }
  },
  "password": "",
  "percentageFee": 6,
  "profileImage": "http://roaminghunger.com/img/trucks/original/5727d9bc-0dfc-430b-816c-712f46204482.jpg",
  "transactionFee": 30,
  "username": ""
}