{
  "address": "",
  "description": "Want something sweet but don't feel like eating any run-of-the-mill treats? Let Sugar Whipped whip you up a delicious pastry! Whether you spot them on the street or hire them to cater your next special event, Sugar Whipped is ready to bring some creative sweetness into your day. Don't miss their delicious gourmet marshmallows or their tasty cake pops!",
  "exampleOrder": "",
  "hours": [
    {
      "closeTime": "",
      "day": "Monday",
      "openTime": ""
    },
    {
      "closeTime": "",
      "day": "Tuesday",
      "openTime": ""
    },
    {
      "closeTime": "",
      "day": "Wednesday",
      "openTime": ""
    },
    {
      "closeTime": "",
      "day": "Thursday",
      "openTime": ""
    },
    {
      "closeTime": "",
      "day": "Friday",
      "openTime": ""
    },
    {
      "closeTime": "",
      "day": "Saturday",
      "openTime": ""
    },
    {
      "closeTime": "",
      "day": "Sunday",
      "openTime": ""
    }
  ],
  "name": "Sugar Whipped Bakery",
  "optional": {
    "producer": {
      "enabled": true,
      "menuLink": "",
      "phoneNumber": ""
    }
  },
  "password": "",
  "percentageFee": 6,
  "profileImage": "http://roaminghunger.com/img/trucks/original/8904/5515bef2-734c-467e-9702-321946204482.jpg",
  "transactionFee": 30,
  "username": ""
}