{
  "address": "",
  "description": "Frosted Frenzy is the Valley's best Gourmet cupcakes! We only use the highest quality ingredients and bake in small batches to guarantee the freshest possible cupcakes. Our menu of 20 different traditional family recipes is sure to please any sweet tooth! We cater weddings, parties, school and corporate events all over the valley. ",
  "exampleOrder": "",
  "hours": [
    {
      "closeTime": "",
      "day": "Monday",
      "openTime": ""
    },
    {
      "closeTime": "",
      "day": "Tuesday",
      "openTime": ""
    },
    {
      "closeTime": "",
      "day": "Wednesday",
      "openTime": ""
    },
    {
      "closeTime": "",
      "day": "Thursday",
      "openTime": ""
    },
    {
      "closeTime": "",
      "day": "Friday",
      "openTime": ""
    },
    {
      "closeTime": "",
      "day": "Saturday",
      "openTime": ""
    },
    {
      "closeTime": "",
      "day": "Sunday",
      "openTime": ""
    }
  ],
  "name": "Frosted Frenzy Cupcakes",
  "optional": {
    "producer": {
      "enabled": true,
      "menuLink": "",
      "phoneNumber": ""
    }
  },
  "password": "",
  "percentageFee": 6,
  "profileImage": "http://roaminghunger.com/img/trucks/original/5310e55d-ef1c-4d93-81a7-5b3a46204482.jpg",
  "transactionFee": 30,
  "username": ""
}