{
  "address": "",
  "description": "Triple Dot is a truck that serves traditional Argentine and Dutch foods, as well as anything they decide tastes good! With the slogan, \"No concept - just random good food,\" you know you are in for a treat. Stop by the truck on the streets of Phoenix for a delicious meal!",
  "exampleOrder": "",
  "hours": [
    {
      "closeTime": "",
      "day": "Monday",
      "openTime": ""
    },
    {
      "closeTime": "",
      "day": "Tuesday",
      "openTime": ""
    },
    {
      "closeTime": "",
      "day": "Wednesday",
      "openTime": ""
    },
    {
      "closeTime": "",
      "day": "Thursday",
      "openTime": ""
    },
    {
      "closeTime": "",
      "day": "Friday",
      "openTime": ""
    },
    {
      "closeTime": "",
      "day": "Saturday",
      "openTime": ""
    },
    {
      "closeTime": "",
      "day": "Sunday",
      "openTime": ""
    }
  ],
  "name": "Triple Dot Food Truck",
  "optional": {
    "producer": {
      "enabled": true,
      "menuLink": "",
      "phoneNumber": ""
    }
  },
  "password": "",
  "percentageFee": 6,
  "profileImage": "http://roaminghunger.com/img/trucks/original/548f82fe-b9b4-4b13-a1c7-73f046204482.jpg",
  "transactionFee": 30,
  "username": ""
}