{
  "address": "",
  "description": "Waffle Love is selling delicious waffle goodness to the streets of the Phoenix area. Try the raspberry nutella, the \"red wonder,\" or a host of other delicious toppings. There are even gluten-free options for the dietarily restricted! Stop by today!",
  "exampleOrder": "",
  "hours": [
    {
      "closeTime": "",
      "day": "Monday",
      "openTime": ""
    },
    {
      "closeTime": "",
      "day": "Tuesday",
      "openTime": ""
    },
    {
      "closeTime": "",
      "day": "Wednesday",
      "openTime": ""
    },
    {
      "closeTime": "",
      "day": "Thursday",
      "openTime": ""
    },
    {
      "closeTime": "",
      "day": "Friday",
      "openTime": ""
    },
    {
      "closeTime": "",
      "day": "Saturday",
      "openTime": ""
    },
    {
      "closeTime": "",
      "day": "Sunday",
      "openTime": ""
    }
  ],
  "name": "Waffle Love AZ",
  "optional": {
    "producer": {
      "enabled": true,
      "menuLink": "",
      "phoneNumber": ""
    }
  },
  "password": "",
  "percentageFee": 6,
  "profileImage": "http://roaminghunger.com/img/trucks/original/54907fb1-17e0-44ad-8ce9-02e246204482.jpg",
  "transactionFee": 30,
  "username": ""
}