{
  "address": "",
  "description": "White Eyes is making its way through every exciting event in the Southwest and serving up deliciously crunchy and fluffy fry bread. This family-run trailer is where you\u2019ll find some of the most flavorful fry bread you may ever try. Their signature dough recipe starts off frozen, but it\u2019s served to you hot, fresh, and fast. You\u2019re free to top your authentic treat with all sorts of tastiness. Ask this team to pile on meat, beans, and veggies, and you\u2019ve got yourself an incredibly scrumptious Indian Taco! For a fabulous dessert, have your fry bread topped with cinnamon sugar or honey or Nutella, (and these are just a few of the yummy choices). For some fantastic fry bread and famously friendly service, be sure to come by White Eyes!",
  "exampleOrder": "",
  "hours": [
    {
      "closeTime": "",
      "day": "Monday",
      "openTime": ""
    },
    {
      "closeTime": "",
      "day": "Tuesday",
      "openTime": ""
    },
    {
      "closeTime": "",
      "day": "Wednesday",
      "openTime": ""
    },
    {
      "closeTime": "",
      "day": "Thursday",
      "openTime": ""
    },
    {
      "closeTime": "",
      "day": "Friday",
      "openTime": ""
    },
    {
      "closeTime": "",
      "day": "Saturday",
      "openTime": ""
    },
    {
      "closeTime": "",
      "day": "Sunday",
      "openTime": ""
    }
  ],
  "name": "White Eyes",
  "optional": {
    "producer": {
      "enabled": true,
      "menuLink": "",
      "phoneNumber": ""
    }
  },
  "password": "",
  "percentageFee": 6,
  "profileImage": "http://roaminghunger.com/img/trucks/original/50ad2d62-1ed8-4370-8d72-673446204482.jpg",
  "transactionFee": 30,
  "username": ""
}