{
  "address": "",
  "description": "Frydeez offers custom gourmet egg rolls filled with delicious meats and fresh ingredients.  Make sure to try their dessert options too!",
  "exampleOrder": "",
  "hours": [
    {
      "closeTime": "",
      "day": "Monday",
      "openTime": ""
    },
    {
      "closeTime": "",
      "day": "Tuesday",
      "openTime": ""
    },
    {
      "closeTime": "",
      "day": "Wednesday",
      "openTime": ""
    },
    {
      "closeTime": "",
      "day": "Thursday",
      "openTime": ""
    },
    {
      "closeTime": "",
      "day": "Friday",
      "openTime": ""
    },
    {
      "closeTime": "",
      "day": "Saturday",
      "openTime": ""
    },
    {
      "closeTime": "",
      "day": "Sunday",
      "openTime": ""
    }
  ],
  "name": "Frydeez",
  "optional": {
    "producer": {
      "enabled": true,
      "menuLink": "",
      "phoneNumber": ""
    }
  },
  "password": "",
  "percentageFee": 6,
  "profileImage": "http://roaminghunger.com/img/trucks/original/537bf3f6-d4ac-4076-b134-400e46204482.png",
  "transactionFee": 30,
  "username": ""
}