{
  "address": "",
  "description": "Authentic Filipino favorites are on the street food scene today! ADOruBOwl is making delicious dishes with traditional methods and ingredients, taking your taste buds on a culinary trip you'll never forget. Savory sandwiches stuffed with sisig and lumpia, and amazing rice bowls that are packed with only the best of the best ingredients are on the menu at this fantastic food truck! Dig into something great today with ADOruBOwl!",
  "exampleOrder": "",
  "hours": [
    {
      "closeTime": "",
      "day": "Monday",
      "openTime": ""
    },
    {
      "closeTime": "",
      "day": "Tuesday",
      "openTime": ""
    },
    {
      "closeTime": "",
      "day": "Wednesday",
      "openTime": ""
    },
    {
      "closeTime": "",
      "day": "Thursday",
      "openTime": ""
    },
    {
      "closeTime": "",
      "day": "Friday",
      "openTime": ""
    },
    {
      "closeTime": "",
      "day": "Saturday",
      "openTime": ""
    },
    {
      "closeTime": "",
      "day": "Sunday",
      "openTime": ""
    }
  ],
  "name": "ADOruBOwl",
  "optional": {
    "producer": {
      "enabled": true,
      "menuLink": "",
      "phoneNumber": ""
    }
  },
  "password": "",
  "percentageFee": 6,
  "profileImage": "http://roaminghunger.com/img/trucks/original/5630fb29-f958-4e8a-b045-7de246204482.jpg",
  "transactionFee": 30,
  "username": ""
}