{
  "address": "",
  "description": "'Q On Wheels Mobile BBQ brings Texas style BBQ with a Las Vegas flair. Specializing in smoked, flavorful Tri-Tip and sausages. Serving the greater Henderson area, 'Q On Wheels brings the 'Q to you!",
  "exampleOrder": "",
  "hours": [
    {
      "closeTime": "",
      "day": "Monday",
      "openTime": ""
    },
    {
      "closeTime": "",
      "day": "Tuesday",
      "openTime": ""
    },
    {
      "closeTime": "",
      "day": "Wednesday",
      "openTime": ""
    },
    {
      "closeTime": "",
      "day": "Thursday",
      "openTime": ""
    },
    {
      "closeTime": "",
      "day": "Friday",
      "openTime": ""
    },
    {
      "closeTime": "",
      "day": "Saturday",
      "openTime": ""
    },
    {
      "closeTime": "",
      "day": "Sunday",
      "openTime": ""
    }
  ],
  "name": "'Q ON WHEELS MOBILE BBQ",
  "optional": {
    "producer": {
      "enabled": true,
      "menuLink": "",
      "phoneNumber": ""
    }
  },
  "password": "",
  "percentageFee": 6,
  "profileImage": "http://roaminghunger.com/img/trucks/original/11021/56dc9111-9960-466c-9d42-4b3a46204482.png",
  "transactionFee": 30,
  "username": ""
}