{
  "address": "",
  "description": "Miami has people coming in from all parts of the world. I feel that this place should be shared with everyone. Let's pull those people away from the stero-typical \"South Beach Miami\" and introduce them to a small part of the REAL Miami.Although it is known to many to be the \"King of the Fritas\", let's make this a place you bring one new friend or visitor every time.",
  "exampleOrder": "",
  "hours": [
    {
      "closeTime": "",
      "day": "Monday",
      "openTime": ""
    },
    {
      "closeTime": "",
      "day": "Tuesday",
      "openTime": ""
    },
    {
      "closeTime": "",
      "day": "Wednesday",
      "openTime": ""
    },
    {
      "closeTime": "",
      "day": "Thursday",
      "openTime": ""
    },
    {
      "closeTime": "",
      "day": "Friday",
      "openTime": ""
    },
    {
      "closeTime": "",
      "day": "Saturday",
      "openTime": ""
    },
    {
      "closeTime": "",
      "day": "Sunday",
      "openTime": ""
    }
  ],
  "name": "El Rey de las Fritas",
  "optional": {
    "producer": {
      "enabled": true,
      "menuLink": "",
      "phoneNumber": ""
    }
  },
  "password": "",
  "percentageFee": 6,
  "profileImage": "http://roaminghunger.com/img/trucks/original/4eb9b45a-ac18-4596-b8f6-29d446204482.jpg",
  "transactionFee": 30,
  "username": ""
}