{
  "address": "",
  "description": "Hungry Heart has embarked on a journey to provide good old \"American wholesome foods\" to the public. The mission is to serve top quality food at an affordable price. Offering pasta, schnitzel, fruit, salad, and more, this truck has just about everything you could want. Check it out today!",
  "exampleOrder": "",
  "hours": [
    {
      "closeTime": "",
      "day": "Monday",
      "openTime": ""
    },
    {
      "closeTime": "",
      "day": "Tuesday",
      "openTime": ""
    },
    {
      "closeTime": "",
      "day": "Wednesday",
      "openTime": ""
    },
    {
      "closeTime": "",
      "day": "Thursday",
      "openTime": ""
    },
    {
      "closeTime": "",
      "day": "Friday",
      "openTime": ""
    },
    {
      "closeTime": "",
      "day": "Saturday",
      "openTime": ""
    },
    {
      "closeTime": "",
      "day": "Sunday",
      "openTime": ""
    }
  ],
  "name": "Hungry Heart",
  "optional": {
    "producer": {
      "enabled": true,
      "menuLink": "",
      "phoneNumber": ""
    }
  },
  "password": "",
  "percentageFee": 6,
  "profileImage": "http://roaminghunger.com/img/trucks/original/543d527f-1fcc-4e18-aa9c-0ea046204482.jpg",
  "transactionFee": 30,
  "username": ""
}